unchaind/__init__.py
unchaind/__main__.py
unchaind/command.py
unchaind/config.py
unchaind/constant.py
unchaind/exception.py
unchaind/hook.py
unchaind/http.py
unchaind/kill.py
unchaind/kills.py
unchaind/log.py
unchaind/notify.py
unchaind/path.py
unchaind/sink.py
unchaind/static.py
unchaind/universe.py
unchaind/util.py
unchaind/data/connection.txt
unchaind/data/system.txt
unchaind/mapper/__init__.py
unchaind/mapper/siggy.py
unchaind/notifier/__init__.py
unchaind/notifier/kill.py
unchaind/notifier/system.py
unchaind-0.1.3.dist-info/LICENSE
unchaind-0.1.3.dist-info/METADATA
unchaind-0.1.3.dist-info/WHEEL
unchaind-0.1.3.dist-info/entry_points.txt
unchaind-0.1.3.dist-info/top_level.txt
unchaind-0.1.3.dist-info/RECORD
