Metadata-Version: 2.1
Name: unchaind
Version: 0.1.3
Summary: Wormhole space kill notification tool for EVE Online.
Home-page: https://github.com/supakeen/unchaind
Author: supakeen
Author-email: cmdr@supakeen.com
License: UNKNOWN
Platform: UNKNOWN
Requires-Dist: click
Requires-Dist: lxml
Requires-Dist: pytoml
Requires-Dist: tornado
Provides-Extra: dev
Requires-Dist: black ; extra == 'dev'
Requires-Dist: flake8 ; extra == 'dev'
Requires-Dist: pre-commit ; extra == 'dev'
Requires-Dist: pytest ; extra == 'dev'
Requires-Dist: pytest-cov ; extra == 'dev'
